treenode/__init__.py
treenode/treenode.py
treenode_py-1.3.0.dist-info/LICENSE
treenode_py-1.3.0.dist-info/METADATA
treenode_py-1.3.0.dist-info/WHEEL
treenode_py-1.3.0.dist-info/top_level.txt
treenode_py-1.3.0.dist-info/RECORD
