Metadata-Version: 2.1
Name: treenode-py
Version: 1.3.0
Summary: treenode-py (treenode) is a Python library that provides functionality to create and manipulate tree structures.
Home-page: https://github.com/PivoSteve/treenode-py
Author: Syra
Author-email: horriblebuba@gmail.com
License: MIT
Project-URL: Source, https://github.com/PivoSteve/treenode-py
Keywords: tree directory file system node structures structure
Classifier: License :: OSI Approved :: MIT License
Classifier: Programming Language :: Python :: 3
Classifier: Programming Language :: Python :: 3.6
Classifier: Programming Language :: Python :: 3.7
Classifier: Programming Language :: Python :: 3.8
Classifier: Programming Language :: Python :: 3.9
License-File: LICENSE
